FewSOLDataLoader/CocoFormatConverter.py
FewSOLDataLoader/DataLoader.py
FewSOLDataLoader/SingleRealPose.py
FewSOLDataLoader/__init__.py
FewSOLDataLoader/file_class_mapper.json
FewSOLDataLoader/helpers.py
FewSOLDataLoader/syn_google_scenes_data_mapper.json
FewSOLDataLoader-0.0.14.dist-info/LICENSE
FewSOLDataLoader-0.0.14.dist-info/METADATA
FewSOLDataLoader-0.0.14.dist-info/WHEEL
FewSOLDataLoader-0.0.14.dist-info/top_level.txt
FewSOLDataLoader-0.0.14.dist-info/RECORD
