Metadata-Version: 2.1
Name: FewSOLDataLoader
Version: 0.0.14
Summary: Pytorch Dataloader for FewSOL
Home-page: https://github.com/IRVLUTD/FewSOL-DataLoader
Author: Jesse Musa, Jishnu P
Author-email: jesse.musa@utdallas.edu, jishnu.p@utdallas.edu
Classifier: Programming Language :: Python :: 3
Classifier: License :: OSI Approved :: MIT License
Classifier: Operating System :: OS Independent
Requires-Python: >=3.0
License-File: LICENSE
Requires-Dist: matplotlib
Requires-Dist: numpy
Requires-Dist: torch
Requires-Dist: torchvision
Requires-Dist: scipy
Requires-Dist: pyyaml
Requires-Dist: easydict
Requires-Dist: transforms3d
Requires-Dist: opencv-python
